stash/__init__.py
stash/_helpers.py
stash/consts.py
stash/defaults.py
stash/manager.py
stash/options.py
stash/codecs/__init__.py
stash/codecs/brotli.py
stash/codecs/bzip2.py
stash/codecs/codec.py
stash/codecs/gzip.py
stash/codecs/lz4.py
stash/codecs/lzf.py
stash/codecs/lzma.py
stash/codecs/lzo.py
stash/codecs/passthru.py
stash/codecs/snappy.py
stash/codecs/zlib.py
stash/codecs/zopfli.py
stash/codecs/zstd.py
stash/serializers/__init__.py
stash/serializers/bson.py
stash/serializers/cbor.py
stash/serializers/default.py
stash/serializers/json.py
stash/serializers/msgpack.py
stash/serializers/orjson.py
stash/serializers/rapidjson.py
stash/serializers/serializer.py
stash/serializers/simplejson.py
stash/serializers/ujson.py
stash/storages/__init__.py
stash/storages/dbm_.py
stash/storages/filesystem.py
stash/storages/leveldb.py
stash/storages/lmdb.py
stash/storages/lsmdb.py
stash/storages/memory.py
stash/storages/mongodb.py
stash/storages/null.py
stash/storages/redis.py
stash/storages/storage.py
stash/utils/__init__.py
stash/utils/checksum.py
stash/utils/nested_path.py
stashlib-0.0.8.0.dist-info/LICENSE
stashlib-0.0.8.0.dist-info/METADATA
stashlib-0.0.8.0.dist-info/WHEEL
stashlib-0.0.8.0.dist-info/top_level.txt
stashlib-0.0.8.0.dist-info/RECORD
