Metadata-Version: 2.1
Name: stashlib
Version: 0.0.8.0
Summary: stash is an extensible and lightweight cache library for python
Home-page: https://github.com/masroore/stash.py
Author: Masroor Ehsan
Author-email: masroore@gmail.com
License: MIT
Keywords: cache caching
Platform: any
Classifier: Development Status :: 4 - Beta
Classifier: Environment :: Other Environment
Classifier: Intended Audience :: Developers
Classifier: License :: OSI Approved :: MIT License
Classifier: Operating System :: OS Independent
Classifier: Programming Language :: Python :: 3.10
Classifier: Programming Language :: Python :: 3.11
Classifier: Programming Language :: Python :: 3.12
Classifier: Topic :: Software Development :: Libraries :: Python Modules
License-File: LICENSE
